{"name":"Moodle-block mamiline","tagline":"Moodle and Mahara are on line.","body":"### mamiline\r\nmamiline(マミライン)はMoodle上に蓄積されている成績情報やアクティビティログを集計し見やすい形での表示をすることで、学生ごとのポートフォリオを作る機能を持っています。\r\n\r\n### 開発経緯\r\nMoodleには成績情報や提出したファイル、フォーラム等への投稿等のアクティビティ情報が蓄積されている。\r\n蓄積量はMoodleの利用年月にもよるが、学生が自身の学習結果・成果を振り返るための情報が相当量蓄積されていると推測することができる。\r\nしかしながら、現在のMoodleには学生が「ふりかえり」をするための機能実装は発達していない。更に学生が「コースをまたいで」成績情報を見る機能は現時点では存在しないか、存在を知られていない。\r\nこれらの事情もあり、MoodleとMaharaを連携させて\"Mahoodle\"として連携させようという動きがあり、Mnet認証をはじめ連携にあたる様々なプラグインも開発されている。 しかしながら、MoodleとMaharaを連携させるには技術的にも困難を伴う。データのやりとりも一方通行(MoodleからMaharaへのやりとりは出来るがMaharaからMoodleへのやりとりは、同時には出来ない、)となる。\r\nそれに付随して認証システムにおける認証情報の継承など、難易度の高い問題をクリアする必要がある。これにより連携コストが大幅に上がっている。\r\nそこで今回は「あえて連携しない」をテーマに、Moodleにあるデータのみを使ってポートフォリオを作成するプラグインを開発した。Maharaと連携しなくても出来ることを、あらゆる手を尽くして実現しているのがこのプラグインの特徴である。 Moodleプラグインとして導入するだけなので、導入コストを抑えることができる。 このプラグインはgithub上への公開しており、今後もプルリクエストを受け付けるなどして機能向上を図る。\r\n\r\n### インストール方法\r\nMoodleのblocksディレクトリに配置します。\r\n\r\n","google":"","note":"Don't delete this file! It's used internally to help with page regeneration."}